{
  "870276": [
    {
      "fileName": "!configanytime-1.0.jar",
      "staged": false,
      "deleted": false,
      "md5": "/qsH6LE3sQh4iKfsmVRrXQ==",
      "fileId": 4576653
    }
  ],
  "419286": [
    {
      "fileName": "!mixinbooter-8.4.jar",
      "staged": false,
      "deleted": false,
      "md5": "G6DLsdkT/+10DYduuG5XoQ==",
      "fileId": 4699275
    }
  ],
  "305840": [
    {
      "fileName": "absentbydesign-1.12.2-1.0.4.jar",
      "staged": false,
      "deleted": false,
      "md5": "DFeiqWl66EZkWv2TuCwSnw==",
      "fileId": 2748065
    }
  ],
  "234851": [
    {
      "fileName": "AbyssalCraft Integration-1.12.2-1.11.2.jar",
      "staged": false,
      "deleted": false,
      "md5": "l6vOz0uvSNWqeQ8gQGxHyA==",
      "fileId": 2959100
    }
  ],
  "53686": [
    {
      "fileName": "AbyssalCraft-1.12.2-1.10.3.jar",
      "staged": false,
      "deleted": false,
      "md5": "0CAnq9aPbArJHS73pn5AgA==",
      "fileId": 3087689
    }
  ],
  "367831": [
    {
      "fileName": "AIReducer-1.12.2-0.3.0.jar",
      "staged": false,
      "deleted": false,
      "md5": "N6CjQplBkIU/eTJlbF8TuQ==",
      "fileId": 3543884
    }
  ],
  "320163": [
    {
      "fileName": "AmbientEnvironment-1.0.2.jar",
      "staged": false,
      "deleted": false,
      "md5": "tLgEVc1ReFy1UUBsZ5djrA==",
      "fileId": 2785546
    }
  ],
  "224472": [
    {
      "fileName": "AppleCore-mc1.12.2-3.4.0.jar",
      "staged": false,
      "deleted": false,
      "md5": "qN1jWoH+1Zvg0YIG/Tg/bg==",
      "fileId": 2969118
    }
  ],
  "248787": [
    {
      "fileName": "AppleSkin-mc1.12-1.0.14.jar",
      "staged": false,
      "deleted": false,
      "md5": "tDWGDVz6I7xT07jhIL6R1A==",
      "fileId": 2987247
    }
  ],
  "321792": [
    {
      "fileName": "AquaAcrobatics-1.15.3.jar",
      "staged": false,
      "deleted": false,
      "md5": "99wuHzG66r/45D57p64New==",
      "fileId": 4496098
    }
  ],
  "364982": [
    {
      "fileName": "ASMC-1.12.2-1.0.2.jar",
      "staged": false,
      "deleted": false,
      "md5": "RKGl0U/UamalSc7SlEO79g==",
      "fileId": 2902440
    }
  ],
  "246996": [
    {
      "fileName": "base-1.12.2-3.14.0.jar",
      "staged": false,
      "deleted": false,
      "md5": "XUyiQQEEuxQY95dNRMxyxw==",
      "fileId": 3440963
    }
  ],
  "227083": [
    {
      "fileName": "Baubles-1.12-1.5.2.jar",
      "staged": false,
      "deleted": false,
      "md5": "lE3sTvP7/U1JjZSnBHryAQ==",
      "fileId": 2518667
    }
  ],
  "282963": [
    {
      "fileName": "bedpatch-2.2-1.12.2.jar",
      "staged": false,
      "deleted": false,
      "md5": "M2/qgFAthKlKBHkcZPGwcQ==",
      "fileId": 2532663
    }
  ],
  "272515": [
    {
      "fileName": "BetterAdvancements-1.12.2-0.1.0.77.jar",
      "staged": false,
      "deleted": false,
      "md5": "kAmk0IDK9NMeTvjtuh+Qzw==",
      "fileId": 2685984
    }
  ],
  "446253": [
    {
      "fileName": "betterbiomeblend-1.12.2-1.1.7-forge.jar",
      "staged": false,
      "deleted": false,
      "md5": "bM3GQVhHkmfHgjdoLpdwQA==",
      "fileId": 3554486
    }
  ],
  "363860": [
    {
      "fileName": "betterchat-1.4.jar",
      "staged": false,
      "deleted": false,
      "md5": "/O5Vg8WzbeMhS/t1QFCSDw==",
      "fileId": 3048407
    }
  ],
  "278406": [
    {
      "fileName": "BetterPlacement-1.0.0-1.jar",
      "staged": false,
      "deleted": false,
      "md5": "9FGGks05fdW+2jkDKJNS9w==",
      "fileId": 2481852
    }
  ],
  "244181": [
    {
      "fileName": "blockdrops-1.12.2-1.4.0.jar",
      "staged": false,
      "deleted": false,
      "md5": "qyjEovcyhtpJ8iTns//Wlg==",
      "fileId": 2509046
    }
  ],
  "228525": [
    {
      "fileName": "Bookshelf-1.12.2-2.3.590.jar",
      "staged": false,
      "deleted": false,
      "md5": "haRNMplElUXkNfXsVfyRSw==",
      "fileId": 2836960
    }
  ],
  "225643": [
    {
      "fileName": "Botania r1.10-364.4.jar",
      "staged": false,
      "deleted": false,
      "md5": "ehl3n6GeN8uftJoKF3AzKw==",
      "fileId": 3330934
    }
  ],
  "309516": [
    {
      "fileName": "Bountiful-1.12.2-2.2.3.jar",
      "staged": false,
      "deleted": false,
      "md5": "w3JGHpmFjCjUr+9VACcYxg==",
      "fileId": 3570157
    }
  ],
  "298187": [
    {
      "fileName": "BuildingGadgets-2.8.4.jar",
      "staged": false,
      "deleted": false,
      "md5": "0WiGGM8d8OCqq1JvtJIrOQ==",
      "fileId": 3005950
    }
  ],
  "266824": [
    {
      "fileName": "Caliper-1.12.2-1.1.46.jar",
      "staged": false,
      "deleted": false,
      "md5": "1rO6HChh+/oHKcORneMfAg==",
      "fileId": 2810222
    }
  ],
  "460609": [
    {
      "fileName": "censoredasm5.14.jar",
      "staged": false,
      "deleted": false,
      "md5": "gtl+fAb9fKoEeP5HzdvvZg==",
      "fileId": 4623985
    }
  ],
  "307152": [
    {
      "fileName": "champions-1.12.2-1.0.11.10.jar",
      "staged": false,
      "deleted": false,
      "md5": "0vulnRd+DerQKLSzeRwWVA==",
      "fileId": 3177947
    }
  ],
  "290433": [
    {
      "fileName": "Chargers-1.12.2-1.2.0.5.jar",
      "staged": false,
      "deleted": false,
      "md5": "YxwS+/6s/S3UsCKc7R5jVA==",
      "fileId": 2989950
    }
  ],
  "308240": [
    {
      "fileName": "cherishedworlds-1.12.2-1.0.1.jar",
      "staged": false,
      "deleted": false,
      "md5": "J4rOTsPEgbNsDCN4/beLOg==",
      "fileId": 2837800
    }
  ],
  "251407": [
    {
      "fileName": "ClientTweaks_1.12.2-3.1.11.jar",
      "staged": false,
      "deleted": false,
      "md5": "CwxYcBJ2swsAW8qK7vKfnA==",
      "fileId": 2624712
    }
  ],
  "289433": [
    {
      "fileName": "cloudcontrol_v1.0.0formc1.12.2.jar",
      "staged": false,
      "deleted": false,
      "md5": "iKmV52IdBJ8/HgisYxABfg==",
      "fileId": 2537228
    }
  ],
  "251985": [
    {
      "fileName": "ConsoleFilter-1.12.2-1.1.1.jar",
      "staged": false,
      "deleted": false,
      "md5": "w8ZBi0uxtgBWpIlg198TLQ==",
      "fileId": 2540604
    }
  ],
  "237065": [
    {
      "fileName": "ContentTweaker-1.12.2-4.10.0.jar",
      "staged": false,
      "deleted": false,
      "md5": "SrMp+eIqK4xiJ2+sXti1mg==",
      "fileId": 3331364
    }
  ],
  "250398": [
    {
      "fileName": "Controlling-3.0.12.2.jar",
      "staged": false,
      "deleted": false,
      "md5": "A+69sqg1qCnwomm47AJU/g==",
      "fileId": 4428378
    }
  ],
  "633720": [
    {
      "fileName": "CraftingTweaks_1.12.2-9.0.1.jar",
      "staged": false,
      "deleted": false,
      "md5": "R63QACE4yanmib2krSjYEQ==",
      "fileId": 3852709
    }
  ],
  "239197": [
    {
      "fileName": "CraftTweaker2-1.12-4.1.20.693.jar",
      "staged": false,
      "deleted": false,
      "md5": "mkCWI5ldDLCAq0Ny34xifg==",
      "fileId": 4731280
    }
  ],
  "286924": [
    {
      "fileName": "CustomSkinLoader_ForgeLegacy-14.17.jar",
      "staged": false,
      "deleted": false,
      "md5": "uEZsP+2ObK9kiRKUY015fg==",
      "fileId": 4642232
    }
  ],
  "231275": [
    {
      "fileName": "Ding-1.12.2-1.0.2.jar",
      "staged": false,
      "deleted": false,
      "md5": "pTZTyIe68sgs61VmPiKipw==",
      "fileId": 2801170
    }
  ],
  "262146": [
    {
      "fileName": "DurabilityViewer-1.12-forge14.21.1.2387-1.6.jar",
      "staged": false,
      "deleted": false,
      "md5": "sEcsYjW7naT3ktlInALv+Q==",
      "fileId": 2851556
    }
  ],
  "255427": [
    {
      "fileName": "Earthworks-1.12-1.3.6.jar",
      "staged": false,
      "deleted": false,
      "md5": "zPEiWElqblk2tuC8be90sw==",
      "fileId": 2486190
    }
  ],
  "250419": [
    {
      "fileName": "EnchantmentDescriptions-1.12.2-1.1.20.jar",
      "staged": false,
      "deleted": false,
      "md5": "DlIArsvU7LpiK0mo0Pbipw==",
      "fileId": 2898966
    }
  ],
  "254818": [
    {
      "fileName": "energyconverters_1.12.2-1.3.7.30.jar",
      "staged": false,
      "deleted": false,
      "md5": "VAd9MtcHWixsjhmR52YQKg==",
      "fileId": 2992813
    }
  ],
  "367706": [
    {
      "fileName": "fancymenu_forge_2.14.9_MC_1.12-1.12.2.jar",
      "staged": false,
      "deleted": false,
      "md5": "YDHWCNWoVVD/6cnztVXxdQ==",
      "fileId": 4655936
    }
  ],
  "228262": [
    {
      "fileName": "fastflyblockbreaking-MC1.9.4-MC1.12.2-1.1.jar",
      "staged": false,
      "deleted": false,
      "md5": "I78OhJchvKBHnwC9DLK+lw==",
      "fileId": 2700983
    }
  ],
  "299540": [
    {
      "fileName": "FastFurnace-1.12.2-1.3.1.jar",
      "staged": false,
      "deleted": false,
      "md5": "uEzIpYfb01/vLbw+C5Q1qg==",
      "fileId": 2706111
    }
  ],
  "334692": [
    {
      "fileName": "findme-1.12.2-1.1.0.jar",
      "staged": false,
      "deleted": false,
      "md5": "FZpZ7/QW6hbK0NyiTkMpUg==",
      "fileId": 2758262
    }
  ],
  "278494": [
    {
      "fileName": "foamfix-0.10.12a-1.12.2.jar",
      "staged": false,
      "deleted": false,
      "md5": "u5s1JhcgQ5NkbE35kWJtlA==",
      "fileId": 3319452
    }
  ],
  "248453": [
    {
      "fileName": "Forgelin-1.8.4.jar",
      "staged": false,
      "deleted": false,
      "md5": "LaefznImXqsFQeVlY204nQ==",
      "fileId": 2785465
    }
  ],
  "271009": [
    {
      "fileName": "ForgivingVoid_1.12.2-1.1.0.jar",
      "staged": false,
      "deleted": false,
      "md5": "DXT59WWFyE6hdz+ALl6Dlg==",
      "fileId": 2863246
    }
  ],
  "280294": [
    {
      "fileName": "FpsReducer-mc1.12.2-1.20.jar",
      "staged": false,
      "deleted": false,
      "md5": "fogEL5Tb/Mup6Dm2QM9ZLg==",
      "fileId": 3362160
    }
  ],
  "310059": [
    {
      "fileName": "future-mc-0.2.11.jar",
      "staged": false,
      "deleted": false,
      "md5": "Py8cu0vUf5zXnPg+bp+92Q==",
      "fileId": 3924863
    }
  ],
  "227657": [
    {
      "fileName": "GlobalGameRules-1.12.2-2.2.7.jar",
      "staged": false,
      "deleted": false,
      "md5": "aj7p+dhSPX6ioreOBWROqA==",
      "fileId": 2654852
    }
  ],
  "557549": [
    {
      "fileName": "HadEnoughItems_1.12.2-4.25.0.jar",
      "staged": false,
      "deleted": false,
      "md5": "LeD4jPNTvOxgNHSKpbjaOw==",
      "fileId": 4571247
    }
  ],
  "296091": [
    {
      "fileName": "HeatAndClimateLib_1.12.2-3.9.3.jar",
      "staged": false,
      "deleted": false,
      "md5": "dxG15fzEWuiPmYmDXTtZVA==",
      "fileId": 3940469
    }
  ],
  "296096": [
    {
      "fileName": "HeatAndClimateMod_1.12.2-3.9.11.jar",
      "staged": false,
      "deleted": false,
      "md5": "sL2ayku7+TcZDRhuhwUgjw==",
      "fileId": 4448881
    }
  ],
  "640802": [
    {
      "fileName": "hecharacters-1.12.2-1.4.0.jar",
      "staged": false,
      "deleted": false,
      "md5": "7cx/UPSG3J5O3BJJNWXX+g==",
      "fileId": 4692307
    }
  ],
  "283235": [
    {
      "fileName": "HuntingDimension-1.12.2-1.0.43.jar",
      "staged": false,
      "deleted": false,
      "md5": "qIS5CdNdB8JiBAfBYxmxTQ==",
      "fileId": 2860453
    }
  ],
  "253449": [
    {
      "fileName": "Hwyla-1.8.26-B41_1.12.2.jar",
      "staged": false,
      "deleted": false,
      "md5": "vKHAadkXHTMdIR0k6KO3cA==",
      "fileId": 2568751
    }
  ],
  "311846": [
    {
      "fileName": "ic2-tweaker-0.2.1\u002Bbuild.4.jar",
      "staged": false,
      "deleted": false,
      "md5": "MzYjMz5hj+ykTXxMdZuosw==",
      "fileId": 4136686
    }
  ],
  "257356": [
    {
      "fileName": "incontrol-1.12-3.9.18.jar",
      "staged": false,
      "deleted": false,
      "md5": "wwEWxV1CfUL+8W3FY6co6g==",
      "fileId": 3101719
    }
  ],
  "242638": [
    {
      "fileName": "industrialcraft-2-2.8.222-ex112.jar",
      "staged": false,
      "deleted": false,
      "md5": "Ic0A9zfe+9rCMhcW00GFYA==",
      "fileId": 3838713
    }
  ],
  "253230": [
    {
      "fileName": "InitialInventory-3.0.0.jar",
      "staged": false,
      "deleted": false,
      "md5": "RKPrwp/pUx7CkOKS0H19hA==",
      "fileId": 2465617
    }
  ],
  "223094": [
    {
      "fileName": "InventoryTweaks-1.64\u002Bdev.151.jar",
      "staged": false,
      "deleted": false,
      "md5": "7/W0TC4QGaJi6v0KqtTEqQ==",
      "fileId": 2923460
    }
  ],
  "228756": [
    {
      "fileName": "ironchest-1.12.2-7.0.72.847.jar",
      "staged": false,
      "deleted": false,
      "md5": "dDF5vDqPUHUe+7AZrMdZqQ==",
      "fileId": 2747935
    }
  ],
  "224535": [
    {
      "fileName": "IvToolkit-1.3.3-1.12.jar",
      "staged": false,
      "deleted": false,
      "md5": "8aI8tuqmgiQMDs2rZeeFfw==",
      "fileId": 2443253
    }
  ],
  "324717": [
    {
      "fileName": "Jade-0.1.0.jar",
      "staged": false,
      "deleted": false,
      "md5": "AFQxHH5xkG8fP4M0rbU2AA==",
      "fileId": 2735905
    }
  ],
  "250702": [
    {
      "fileName": "jecharacters-1.12.0-3.7.2.jar",
      "staged": false,
      "deleted": false,
      "md5": "meZCaP94OfWZResrY2cJwg==",
      "fileId": 4692184
    }
  ],
  "616190": [
    {
      "fileName": "JEI-Utilities-1.12.2-0.2.12.jar",
      "staged": false,
      "deleted": false,
      "md5": "MFMxgTUCeAaKT8z/+mWZhg==",
      "fileId": 4630499
    }
  ],
  "32274": [
    {
      "fileName": "journeymap-1.12.2-5.7.1.jar",
      "staged": false,
      "deleted": false,
      "md5": "gWC5cPwUz/MN/yeFu5+WTA==",
      "fileId": 2916002
    }
  ],
  "240630": [
    {
      "fileName": "JustEnoughResources-1.12.2-0.9.3.203.jar",
      "staged": false,
      "deleted": false,
      "md5": "tJwARIApYTO71vHM6n8nYw==",
      "fileId": 4440935
    }
  ],
  "410295": [
    {
      "fileName": "konkrete_forge_1.6.1_MC_1.12-1.12.2.jar",
      "staged": false,
      "deleted": false,
      "md5": "TRtFv+CLP3ur58vqAhTKlw==",
      "fileId": 4514895
    }
  ],
  "602731": [
    {
      "fileName": "Loading-Progress-Bar-v1.0-mc[1.8-1.12.2].jar",
      "staged": false,
      "deleted": false,
      "md5": "4H61d/0Z4OIn1KSeC/HB+w==",
      "fileId": 3728182
    }
  ],
  "255257": [
    {
      "fileName": "LootTweaker-0.3.1\u002BMC1.12.2.jar",
      "staged": false,
      "deleted": false,
      "md5": "DXSIbu5+J1YmnoNi4N/TLw==",
      "fileId": 3507866
    }
  ],
  "275321": [
    {
      "fileName": "mctitle-1.0.jar",
      "staged": false,
      "deleted": false,
      "md5": "to3I0ImKbbUae+gkXAcUiw==",
      "fileId": 2468541
    }
  ],
  "359540": [
    {
      "fileName": "mcw-furniture-1.0.1-mc1.12.2beta.jar",
      "staged": false,
      "deleted": false,
      "md5": "rNP89FSegdexebTCE5J+XQ==",
      "fileId": 2909603
    }
  ],
  "502649": [
    {
      "fileName": "MiniEffects-1.12.2-1.1.0.jar",
      "staged": false,
      "deleted": false,
      "md5": "GEGrtopFDZ+omgk6Z5w9Ow==",
      "fileId": 4392199
    }
  ],
  "368098": [
    {
      "fileName": "MMLib-2.3.0.jar",
      "staged": false,
      "deleted": false,
      "md5": "VcCV2gWw9KJbLnV0WtoJTw==",
      "fileId": 3254750
    }
  ],
  "629058": [
    {
      "fileName": "modernsplash-1.12.2-1.3.jar",
      "staged": false,
      "deleted": false,
      "md5": "POZG345fp0lFB/aILIyfdw==",
      "fileId": 4718724
    }
  ],
  "220954": [
    {
      "fileName": "modtweaker-4.0.20.11.jar",
      "staged": false,
      "deleted": false,
      "md5": "94u/sDgte8w3wXSdi+Pndg==",
      "fileId": 3840577
    }
  ],
  "461660": [
    {
      "fileName": "mousetweaks-1.12.2-3.1.4.jar",
      "staged": false,
      "deleted": false,
      "md5": "groHjTDsmAxxf7Y4yjNibg==",
      "fileId": 4661407
    }
  ],
  "253211": [
    {
      "fileName": "MTLib-3.0.7.jar",
      "staged": false,
      "deleted": false,
      "md5": "dDBAR3I7NUjZJoPDl2NoYg==",
      "fileId": 3308160
    }
  ],
  "311927": [
    {
      "fileName": "Nimble-0.0.2.jar",
      "staged": false,
      "deleted": false,
      "md5": "VUFpVmX3ModBMMDNpdbLVQ==",
      "fileId": 2664662
    }
  ],
  "621966": [
    {
      "fileName": "NoLocalizationConflict-1.3.jar",
      "staged": false,
      "deleted": false,
      "md5": "dgzR112D9dbNVq5JfI6cvA==",
      "fileId": 4205587
    }
  ],
  "226779": [
    {
      "fileName": "NoMobSpawningOnTrees-1.2.2-mc1.12.2.jar",
      "staged": false,
      "deleted": false,
      "md5": "l0FOzP2alm8B2ILc/cv6ZQ==",
      "fileId": 2563292
    }
  ],
  "864845": [
    {
      "fileName": "NonConflictKeys-Forge-1.12.2-1.0.0.jar",
      "staged": false,
      "deleted": false,
      "md5": "TG1Jz6pWsDioJJ6myJ4qmg==",
      "fileId": 4547892
    }
  ],
  "256359": [
    {
      "fileName": "NonUpdate-AllMCVersion-Final-2.0.2-universal.jar",
      "staged": false,
      "deleted": false,
      "md5": "OBxqdhDk4tjkyl21KrD6tQ==",
      "fileId": 2656640
    }
  ],
  "284904": [
    {
      "fileName": "noRecipeBook_v1.2.2formc1.12.2.jar",
      "staged": false,
      "deleted": false,
      "md5": "xPozwFpF2zPF3Q+mvsgsYQ==",
      "fileId": 2568865
    }
  ],
  "624960": [
    {
      "fileName": "Nothirium-1.12.2-0.2.4-beta.jar",
      "staged": false,
      "deleted": false,
      "md5": "7AnJdyyRv5xLlx2TfGKh0Q==",
      "fileId": 4438616
    }
  ],
  "408853": [
    {
      "fileName": "particleculling-1.12.2-v1.4.1.jar",
      "staged": false,
      "deleted": false,
      "md5": "1gbgDTze8jG0bUQ3JeZUcQ==",
      "fileId": 4439001
    }
  ],
  "306770": [
    {
      "fileName": "Patchouli-1.0-23.6.jar",
      "staged": false,
      "deleted": false,
      "md5": "VFBHfBznGJxe4RWV1eA6fA==",
      "fileId": 3162874
    }
  ],
  "554387": [
    {
      "fileName": "persistency-1.2.0.jar",
      "staged": false,
      "deleted": false,
      "md5": "jMWk3aDalGpr0lKCxj3gGw==",
      "fileId": 3556105
    }
  ],
  "334601": [
    {
      "fileName": "PogoSticks-1.12.2-1.3.1.jar",
      "staged": false,
      "deleted": false,
      "md5": "vNq77XhYAHmx2vooDWEa7w==",
      "fileId": 2761802
    }
  ],
  "285612": [
    {
      "fileName": "randompatches-1.12.2-1.22.1.10.jar",
      "staged": false,
      "deleted": false,
      "md5": "37sw/zluZCa6mihLBMe88w==",
      "fileId": 3133651
    }
  ],
  "258205": [
    {
      "fileName": "randomtweaks-1.12.2-2.8.3.1.jar",
      "staged": false,
      "deleted": false,
      "md5": "vd9yNah3MrraNOJHTXvulw==",
      "fileId": 3204340
    }
  ],
  "749722": [
    {
      "fileName": "rawinput-1.12.2-1.4.2.jar",
      "staged": false,
      "deleted": false,
      "md5": "mA3vWB68iGYU/MoGc2rbmQ==",
      "fileId": 4540440
    }
  ],
  "556777": [
    {
      "fileName": "ReachFix-1.12.2-1.0.9.jar",
      "staged": false,
      "deleted": false,
      "md5": "zaWJ5BcDuUUqb5XoDiOywQ==",
      "fileId": 4633407
    }
  ],
  "629858": [
    {
      "fileName": "recipesearchbuttons-1.12.2-1.0.1.jar",
      "staged": false,
      "deleted": false,
      "md5": "R9OACEKpirhUkDRuYZHxoA==",
      "fileId": 3816276
    }
  ],
  "223150": [
    {
      "fileName": "RecurrentComplex-1.4.8.5.jar",
      "staged": false,
      "deleted": false,
      "md5": "W3GM2SwlJkJ+h3yyqZpclw==",
      "fileId": 4643434
    }
  ],
  "270789": [
    {
      "fileName": "RedstoneFlux-1.12-2.1.1.1-universal.jar",
      "staged": false,
      "deleted": false,
      "md5": "k7FxXwW+GHjak/yjbdN/Kg==",
      "fileId": 2920436
    }
  ],
  "624967": [
    {
      "fileName": "RenderLib-1.12.2-1.2.8.jar",
      "staged": false,
      "deleted": false,
      "md5": "8SCtCGGUKnDtONUISxm0yg==",
      "fileId": 4486119
    }
  ],
  "226447": [
    {
      "fileName": "ResourceLoader-MC1.12.1-1.5.3.jar",
      "staged": false,
      "deleted": false,
      "md5": "URQeiC+WznVrmz0l8qzfVw==",
      "fileId": 2477566
    }
  ],
  "333079": [
    {
      "fileName": "Sakura-1.0.7-1.12.2.jar",
      "staged": false,
      "deleted": false,
      "md5": "4MAe0Lx9TVuc+6WEHNVc3A==",
      "fileId": 3254753
    }
  ],
  "693961": [
    {
      "fileName": "screenshot_viewer-1.1.1-forge-mc1.12.2.jar",
      "staged": false,
      "deleted": false,
      "md5": "MSLQKezmq8oHvg8BY3NQJQ==",
      "fileId": 4236445
    }
  ],
  "291788": [
    {
      "fileName": "ServerTabInfo-1.12.2-1.2.6.jar",
      "staged": false,
      "deleted": false,
      "md5": "w9foVo5ncWnaHtnkponfFw==",
      "fileId": 2798112
    }
  ],
  "253861": [
    {
      "fileName": "shulkerbox-1.3.2.jar",
      "staged": false,
      "deleted": false,
      "md5": "FOq+4CfeQlZ34ulqmgMIIw==",
      "fileId": 2856313
    }
  ],
  "321283": [
    {
      "fileName": "SimpleTextOverlay-1.12.2-1.0.0.2.jar",
      "staged": false,
      "deleted": false,
      "md5": "uIZ2MpdUEPm6X9WMf1cQzg==",
      "fileId": 2712327
    }
  ],
  "399669": [
    {
      "fileName": "simpletomb-1.12.2-1.0.0.jar",
      "staged": false,
      "deleted": false,
      "md5": "Roq3M9UG4/6a2X/Y2N2HRA==",
      "fileId": 3024234
    }
  ],
  "310187": [
    {
      "fileName": "SJAP-1.6.0.jar",
      "staged": false,
      "deleted": false,
      "md5": "64YzAIUz9LSCDP3NQ8ssgg==",
      "fileId": 3119004
    }
  ],
  "241596": [
    {
      "fileName": "SlashBlade-mc1.12-r33.jar",
      "staged": false,
      "deleted": false,
      "md5": "rW9cxnE5r8GyNQkDrR71WA==",
      "fileId": 3039993
    }
  ],
  "319175": [
    {
      "fileName": "Sledgehammer-1.12.2-2.0.23.jar",
      "staged": false,
      "deleted": false,
      "md5": "5KawZq7VNLhEtXtwAcKqVg==",
      "fileId": 4501752
    }
  ],
  "254144": [
    {
      "fileName": "soundreloader-1.2-1.12.2.jar",
      "staged": false,
      "deleted": false,
      "md5": "34vtoV8exW/pvq39/N9EyQ==",
      "fileId": 2507277
    }
  ],
  "284754": [
    {
      "fileName": "SpawnerControl-1.6.3b.jar",
      "staged": false,
      "deleted": false,
      "md5": "GAmSnxPqbRbL8DA2/R5Pfg==",
      "fileId": 2725062
    }
  ],
  "275425": [
    {
      "fileName": "subpocket-1.12-2.0.0.1.jar",
      "staged": false,
      "deleted": false,
      "md5": "26v9MBuhihWXRY6qGacyVg==",
      "fileId": 3141755
    }
  ],
  "363856": [
    {
      "fileName": "supersoundmuffler-revived_1.12.2_1.0.2.10.jar",
      "staged": false,
      "deleted": false,
      "md5": "4s3vQ23+HvnYYpoa+CHAYw==",
      "fileId": 2886150
    }
  ],
  "295765": [
    {
      "fileName": "tc6aspects4jei-0.0.2a.jar",
      "staged": false,
      "deleted": false,
      "md5": "WABFvVbjSLMGKcz7N2yXmg==",
      "fileId": 2579495
    }
  ],
  "223628": [
    {
      "fileName": "Thaumcraft-1.12.2-6.1.BETA26.jar",
      "staged": false,
      "deleted": false,
      "md5": "OxN4PMqvtdW5zoy4Xof/9g==",
      "fileId": 2629023
    }
  ],
  "238003": [
    {
      "fileName": "ThaumicInventoryScanning_1.12.2-2.0.10.jar",
      "staged": false,
      "deleted": false,
      "md5": "BqDIC3hKNA4fmpHhBO22RA==",
      "fileId": 2559089
    }
  ],
  "306385": [
    {
      "fileName": "TLS-2.1.8-1.12.2.jar",
      "staged": false,
      "deleted": false,
      "md5": "78ftr68ewOCdIaCvPbVdMA==",
      "fileId": 3314856
    }
  ],
  "317469": [
    {
      "fileName": "TofuCraftReload-0.1.0.9.jar",
      "staged": false,
      "deleted": false,
      "md5": "1ZywHiEK+j322cAjoPCzoA==",
      "fileId": 3115668
    }
  ],
  "254268": [
    {
      "fileName": "torchmaster_1.12.2-1.8.5.0.jar",
      "staged": false,
      "deleted": false,
      "md5": "XSQv8cS9Q08Lhlq+yPe0oA==",
      "fileId": 3529742
    }
  ],
  "355044": [
    {
      "fileName": "touhoulittlemaid-1.12.2-1.2.5-release.jar",
      "staged": false,
      "deleted": false,
      "md5": "TRXW8vtdea463RVDcJs3/g==",
      "fileId": 3576415
    }
  ],
  "281905": [
    {
      "fileName": "TP\u002B-1.12.2-1.0.1.1.jar",
      "staged": false,
      "deleted": false,
      "md5": "IFY5dYUd3yY7/+ttcZokFw==",
      "fileId": 2515952
    }
  ],
  "235577": [
    {
      "fileName": "TrashSlot_1.12.2-8.4.10.jar",
      "staged": false,
      "deleted": false,
      "md5": "OO5v/ESn/uX+hfS/uZdtgw==",
      "fileId": 2722385
    }
  ],
  "250241": [
    {
      "fileName": "TreeChopper-1.12.2-1.2.4.jar",
      "staged": false,
      "deleted": false,
      "md5": "Vt+1GoZMszVfDwTN4n5E1g==",
      "fileId": 2492770
    }
  ],
  "227639": [
    {
      "fileName": "twilightforest-1.12.2-3.11.1021-universal.jar",
      "staged": false,
      "deleted": false,
      "md5": "CTN2CUNyEVTzIIeCMG8E1g==",
      "fileId": 3051450
    }
  ],
  "705000": [
    {
      "fileName": "UniversalTweaks-1.12.2-1.8.0.jar",
      "staged": false,
      "deleted": false,
      "md5": "maYQEbSzqX5wlT2aOw5Xsw==",
      "fileId": 4704976
    }
  ],
  "376040": [
    {
      "fileName": "vanillaanvilrepair-1.1.jar",
      "staged": false,
      "deleted": false,
      "md5": "OtWuFh+Ax+jI2Kx3E2bwTw==",
      "fileId": 2943808
    }
  ],
  "322730": [
    {
      "fileName": "vaultopic-2.2.jar",
      "staged": false,
      "deleted": false,
      "md5": "iTD0YbyVQN27NBcCijs2KQ==",
      "fileId": 2858289
    }
  ],
  "79287": [
    {
      "fileName": "WailaHarvestability-mc1.12-1.1.12.jar",
      "staged": false,
      "deleted": false,
      "md5": "C9h2X/MGS+M2yxsJII5BDA==",
      "fileId": 2481605
    }
  ],
  "295319": [
    {
      "fileName": "walljump-1.12.2-1.3.2.jar",
      "staged": false,
      "deleted": false,
      "md5": "hFvf90L0T0ICFFjqKJcpHg==",
      "fileId": 2865090
    }
  ],
  "576946": [
    {
      "fileName": "WrapFix-1.1.1-beta.jar",
      "staged": false,
      "deleted": false,
      "md5": "j++UN9xkNZA7nwvXuSGTJg==",
      "fileId": 4733169
    }
  ],
  "344787": [
    {
      "fileName": "xptome-1.12.2-v2.0.1.jar",
      "staged": false,
      "deleted": false,
      "md5": "1HeUTmL61VxdmAIiROcpyg==",
      "fileId": 3648989
    }
  ],
  "482566": [
    {
      "fileName": "YARCF-0.14(1.12.2).jar",
      "staged": false,
      "deleted": false,
      "md5": "CzG7qxIlQCBegFDBsdeIsg==",
      "fileId": 3310627
    }
  ],
  "401178": [
    {
      "fileName": "zenutils-1.14.10.jar",
      "staged": false,
      "deleted": false,
      "md5": "5w2T+UAy9qm0JrNq3+yg7g==",
      "fileId": 4733272
    }
  ],
  "357178": [
    {
      "fileName": "_MixinBootstrap-1.1.0.jar",
      "staged": false,
      "deleted": false,
      "md5": "nfDcYo6814cnD0h/u/gVeg==",
      "fileId": 3437402
    }
  ]
}